Workbook

Sheet 入力データ
B1: 会社名 | D1: 日付
C2: この色の部分を打ち込む
C3: 資本の部合計(純資産） | E3: 負債及び純資産合計
B4: 自己資本比率 | D4: ÷ | F4: ×１００
C5: 短期借入金＋長期借入金＋社債 | E5: 資本の部合計(純資産）
B6: ギアリング比率 | D6: ÷ | F6: ×１００
C7: 固定資産合計 | E7: 固定負債＋自己資本
B8: 固定長期適合率 | D8: ÷ | F8: ×１００
C9: 流動資産合計 | E9: 流動負債合計
B10: 流動比率 | D10: ÷ | F10: ×１００
C11: 経常利益 | E11: 当期売上高
B12: 売上高経常利益率 | D12: ÷ | F12: ×１００
C13: 経常利益 | E13: 負債及び純資産合計
B14: 総資本経常利益率（ROA) | D14: ÷ | F14: ×１００
C15: 経常利益-前期経常利益 | E15: 前期経常利益
B16: 経常利益増加率 | D16: ÷ | F16: ×１００
C17: 短期借入金＋長期借入金＋社債 | E17: 経常利益＋減価償却費－法人税等
B18: 債務償還年数 | D18: ÷ | F18: ×１００
C19: 営業利益＋受取利息・配当金 | E19: 支払利息・割引き料
B20: インタレスト・カバレッジ・レシオ | D20: ÷ | F20: ×１００
C21: 営業利益＋当期減価償却実施額
B22: キャッシュフロー額
B23: 事業者に有利な年数 | C23: 有利子負債-現預金-売掛金 | E23: 経常利益＋減価償却費－法人税等
B24: 債務償還年数② | D24: ÷ | F24: ×１００

Sheet 結果
B2: =入力データ!C1 -> 0
C4: 結果 | D4: 位 | E4: 配点 | G4: 評価
A5: 1 | B5: 安全性項目 | C5: 自動計算項目
B6: 自己資本比率 | C6: =入力データ!C4/入力データ!E4*100 -> #DIV/0! | D6: ％ | E6: =_xlfn.IFS(C6>=60,10,C6>=50,9,C6>=40,8,C6>=35,7,C6>=30,6,C6>=25,5,C6>=20,3,C6>=15,1,TRUE,0) -> #DIV/0!
B7: ギアリング比率 | C7: =入力データ!C6/入力データ!E6*100 -> #DIV/0! | D7: ％ | E7: =_xlfn.IFS(C7<=50,10,C7<=100,8,C7<=150,6,C7<=200,4,C7<=250,2,TRUE,0) -> #DIV/0!
B8: 固定長期適合率 | C8: =入力データ!C8/入力データ!E8*100 -> #DIV/0! | D8: ％ | E8: =_xlfn.IFS(C8<=50,7,C8<=60,5,C8<=80,3,C8<=100,1,TRUE,0) -> #DIV/0!
B9: 流動比率 | C9: =入力データ!C10/入力データ!E10*100 -> #DIV/0! | D9: ％ | E9: =_xlfn.IFS(C9>=160,7,C9>=140,5,C9>=120,3,C9>=100,1,TRUE,0) -> #DIV/0!
A11: 2 | B11: 収益性項目
B12: 売上高経常利益率 | C12: =入力データ!C12/入力データ!E12*100 -> #DIV/0! | D12: ％ | E12: =_xlfn.IFS(C12<0,0,C12>=4,5,C12>=3,4,C12>=2,3,C12>=1,2,TRUE,1) -> #DIV/0!
B13: 総資本経常利益率 | C13: =入力データ!C14/入力データ!E14*100 -> #DIV/0! | D13: ％ | E13: =_xlfn.IFS(C13<0,0,C13>=3,5,C13>=1,3,TRUE,1) -> #DIV/0! | I13: スコア | J13: 格付け
B14: 収益フロー | C14: 3期連続黒字 | E14: =_xlfn.IFS(C14="3期連続黒字",5,C14="2期連続黒字",3,TRUE,0) -> 5 | I14: 90以上 | J14: 1 | K14: 倒産指数０
I15: 80以上 | J15: 2 | K15: 超優良企業
A16: 3 | B16: 成長性項目 | I16: 65以上 | J16: 3 | K16: 優良企業
B17: 経常利益増加率 | C17: =入力データ!C16/入力データ!E16*100 -> #DIV/0! | D17: ％ | E17: =_xlfn.IFS(C17>=30,5,C17>=20,4,C17>=15,3,C17>=10,2,C17>=5,1,TRUE,0) -> #DIV/0! | I17: 50以上 | J17: 4 | K17: 良好
B18: 自己資本額 | E18: =IF(C18="",0,_xlfn.IFS(C18<0,0,C18>10000000000,15,C18>7000000000,12,C18>5000000000,10,C18>3000000000,8,C18>1000000000,7,C18>700000000,6,C18>500000000,5,C18>300000000,4,C18>100000000,3,C18>50000000,2,TRUE,1)) -> 0 | I18: 40以上 | J18: 5 | K18: 普通
B19: 売上高 | E19: =IF(C19="",0,_xlfn.IFS(C19>=100000000000,15,C19>=10000000000,10,C19>=5000000000,7,C19>=3000000000,5,C19>=1000000000,3,C19>=500000000,2,C19>=100000000,1,TRUE,0)) -> 0 | I19: 25以上 | J19: 6 | K19: やや普通
I20: 25未満 | J20: 7 | K20: やや警戒
A21: 4 | B21: 返済能力 | I21: 警戒先 | J21: 8
B22: 債務償還年数 | C22: =入力データ!C18/入力データ!E18 -> #DIV/0! | D22: 年 | E22: =_xlfn.IFS(C22<0,0,C22<=1,20,C22<=3,17,C22<=5,14,C22<=7,11,C22<=9,8,C22<=12,5,C22<=15,3,C22<=20,2,TRUE,1) -> #DIV/0! | I22: 延滞先 | J22: 9
B23: インタレスト・カバレッジ・レシオ | C23: =入力データ!C20/入力データ!E20 -> #DIV/0! | D23: 倍 | E23: =_xlfn.IFS(C23<1,0,C23>5,15,C23>4,12,C23>3,10,C23>2.5,8,C23>2,7,C23>1.75,6,C23>1.5,4,C23>1.25,3,TRUE,2) -> #DIV/0! | I23: 事故先 | J23: 10
B24: キャッシュフロー額 | C24: =入力データ!C22 -> 0 | E24: =_xlfn.IFS(C24<0,0,C24>10000000000,20,C24>7000000000,18,C24>5000000000,16,C24>3000000000,14,C24>1000000000,12,C24>700000000,10,C24>500000000,8,C24>300000000,6,C24>100000000,4,TRUE,2) -> 2
B25: 事業者に有利な債務償還年数 | C25: =MAX(0,入力データ!C24/入力データ!E24) -> #DIV/0! | D25: 年 | I25: 定量要因
B26: 定量要因小計 | E26: =SUM(E5:E25) -> #DIV/0! | I26: 格付け判定 | J26: =E26 -> #DIV/0!
E27: 主観項目
B28: 市場動向
B29: 景気感応度 | I29: スコア | J29: 格付け
B30: 市場規模 | I30: 180以上 | J30: 1 | K30: リスクなし
B31: 競合状態 | I31: 160以上 | J31: 2 | K31: 殆どリスクなし
B32: 業歴 | I32: 130以上 | J32: 3 | K32: リスク些少
B33: 経営者・経営方針 | I33: 100以上 | J33: 4 | K33: リスクあるが良好水準
B34: 株主 | I34: 80以上 | J34: 5 | K34: リスクあるが平均的水準
B35: 従業員モラル | I35: 50以上 | J35: 6 | K35: リスクやや高いが許容範囲
B36: 営業基盤 | I36: 50未満 | J36: 7 | K36: リスク高く管理徹底
B37: 競争力 | I37: 警戒先 | J37: 8 | K37: 行き詰まる可能性あり
B38: シェア | I38: 延滞先 | J38: 9 | K38: 回復難しく不良債権解消目処なし
I39: 事故先 | J39: 10 | K39: 償却を要する
B40: 定性要因小計 | E40: =SUM(E28:E38) -> 0
I41: 定量・定性要因
B42: スコア合計 | E42: =E26+E40 -> #DIV/0! | I42: 格付け判定 | J42: =E42+J26 -> #DIV/0!

Sheet スコア表
B1: 定量要因
C2: 配点 | D2: 0 | E2: 1 | F2: 2 | G2: 3 | H2: 4 | I2: 5 | J2: 6 | K2: 7 | L2: 8 | M2: 9 | N2: 10 | O2: 11 | P2: 12 | Q2: 14 | R2: 15 | S2: 16 | T2: 17 | U2: 18 | V2: 20
B4: 安全性項目
B5: 自己資本比率 | C5: 10 | D5: １５％未満 | E5: １５％以上 | G5: ２０％以上 | I5: ２５％以上 | J5: ３０％以上 | K5: ３５％以上 | L5: ４０％以上 | M5: ５０％以上 | N5: ６０＆以上
B6: ギアリング比率 | C6: 10 | D6: ２５０％超 | F6: ２５０％以内 | H6: ２００％以内 | J6: １５０％以内 | L6: １００％以内 | N6: ５０％以内
B7: 固定長期適合率 | C7: 7 | D7: １００％超 | E7: １００％以内 | G7: ８０％以内 | I7: ６０％以内 | K7: ５０％以内
B8: 流動比率 | C8: 7 | D8: 100未満 | E8: １００％以上 | G8: １２０％以上 | I8: １４０％以上 | K8: １６０％以上
B10: 収益性項目
B11: 売上高経常利益率 | C11: 5 | D11: マイナス | E11: １％未満 | F11: １％以上 | G11: ２％以上 | H11: ３％以上 | I11: ４％以上
B12: 総資本経常利益率 | C12: 5 | D12: マイナス | E12: １％未満 | G12: １％以上 | I12: ３％以上
B13: 収益フロー | C13: 5 | D13: その他 | G13: 2期連続黒字 | I13: 3期連続黒字
B15: 成長性項目
B16: 経常利益増加率 | C16: 5 | D16: ５％未満 | E16: ５％以上 | F16: １０％以上 | G16: １５％以上 | H16: ２０％以上 | I16: ３０％以上
B17: 自己資本額 | C17: 15 | D17: 債務超過 | E17: ５０００万以下 | F17: １億円以下 | G17: 3億円以下 | H17: 5億円以下 | I17: 7億円以下 | J17: 10億円以下 | K17: 30億円以下 | L17: 50億円以下 | N17: 70億円以下 | P17: 100億円以下 | R17: 100億円超
B18: 売上高 | C18: 5 | D18: 1億未満 | E18: 1億円以上 | F18: 5億以上 | G18: 10億円以上 | I18: 30億円以上 | K18: 50億円以上 | N18: 100億円以上 | R18: 1000億以上
B20: 返済能力
B21: 債務償還年数 | C21: 20 | D21: マイナス | E21: 20年超 | F21: 20年以内 | G21: 15年以内 | I21: 12年以内 | L21: 9年以内 | O21: 7年以内 | Q21: 5年以内 | T21: 3年以内 | V21: 1年以内
B22: インタレスト・カバレッジ・レシオ | C22: 15 | D22: 1倍未満 | F22: 1.25倍以内 | G22: １．５倍以内 | H22: 1.75倍以内 | J22: 2倍以内 | K22: 2.5倍以内 | L22: 3倍以内 | N22: 4倍以内 | P22: 5倍以内 | R22: 5倍超
B23: キャッシュフロー額 | C23: 20 | D23: マイナス | F23: 1億円以下 | H23: 3億円以下 | J23: 5億円以下 | L23: 7億円以下 | N23: 10億円以下 | P23: 30億円以下 | Q23: 50億円以下 | S23: 70億円以下 | U23: 100億円以下 | V23: 100億円超
D24: 懸念（根本的な解決へ） | F24: 注意（新規融資厳しめ） | H24: 普通（保証協会付） | J24: 良好（プロパー狙える）
B25: 債務償還年数（優しい） | C25: 無 | D25: ２０年超 | F25: １５年以上 | H25: １０～１５年 | J25: １０年未満
B27: 定性要因
C28: 配点 | D28: 10 | E28: 8 | F28: 7 | G28: 6 | H28: 5 | I28: 4 | J28: 3 | K28: 2 | L28: 1 | M28: 0
B29: 市場動向 | C29: 10 | D29: 成長期 | E29: 成熟期 | G29: 導入期 | H29: 飽和期 | J29: 衰退期 | M29: 急減期 | N29: 主に主観
B30: 景観感応度 | C30: 3 | J30: 高い | L30: 普通 | M30: 低い | N30: 地域特性や景気による業況影響
B31: 市場規模 | C31: 4 | I31: 1兆円以上 | J31: 1000億円以上 | K31: 300億円以上 | M31: 300億円未満 | N31: 業界の市場規模
B32: 競合状態 | C32: 7 | F32: 独占 | H32: 競合緩やか | K32: 競合激しい | M32: 適当競争
B33: 業歴 | C33: 5 | H33: 30年以上 | J33: 10年以上 | L33: 5年以上 | M33: 5年未満
B34: 経営者・経営方針 | C34: 10 | D34: 優良 | F34: 良好 | H34: 普通 | J34: やや劣る | M34: 劣る | N34: 対外的な評価？
B35: 株主 | C35: 5 | H35: 上場かつ安定 | J35: 上場かつ大 きな問題なし | L35: 非上場だが安定 | M35: 問題あり
B36: 従業員のモラル | C36: 3 | J36: 問題なし | K36: 問題あるが 影響なし | M36: 経営に影響あり | N36: モラル・活気・オフィス内や環境整備
B37: 営業基盤 | C37: 10 | D37: 極めて強固 | F37: 強固 | H37: 相応の基盤あり | K37: やや劣る | M37: 劣る | N37: 販売体制や供給能力・顧客サポート体制など
B38: 競争力 | C38: 7 | F38: 非常に強い | H38: 強い | J38: 普通 | K38: やや劣る | M38: 劣る | N38: 今後3～5年生き残っていけるか？
B39: シェア率（世帯数） | C39: 7 | F39: 地域１５％ | H39: 地域１０％ | J39: 地域５％ | K39: 普通・限定地域で独占 | L39: 地域１％ | M39: やや劣る | N39: 地域での顧客獲得率
B56: パス 1111

Sheet 安全指標について
